browser_extension/__init__.py
browser_extension/browsers/__init__.py
browser_extension/browsers/chrome.py
browser_extension/core/__init__.py
browser_extension/core/config.py
browser_extension/core/constants.py
browser_extension/core/downloader.py
browser_extension/exceptions/__init__.py
browser_extension/exceptions/base.py
browser_extension/exceptions/parse_exception.py
browser_extension/utils/__init__.py
browser_extension-1.0.0.dist-info/LICENSE
browser_extension-1.0.0.dist-info/METADATA
browser_extension-1.0.0.dist-info/WHEEL
browser_extension-1.0.0.dist-info/top_level.txt
browser_extension-1.0.0.dist-info/RECORD
