Metadata-Version: 2.1
Name: browser-extension
Version: 1.0.0
Summary: Download browser extensions
Home-page: https://github.com/batuhan0sanli/browser_extension
Author: batuhan0sanli
Author-email: batuhansanli@gmail.com
License: MIT
Keywords: browser extension download selenium chrome chromium webdriver
Classifier: Development Status :: 3 - Alpha
Classifier: Intended Audience :: Developers
Classifier: Topic :: Software Development :: Build Tools
Classifier: License :: OSI Approved :: MIT License
Classifier: Programming Language :: Python :: 3
Classifier: Programming Language :: Python :: 3.8
Requires-Python: >=3.8
License-File: LICENSE
Requires-Dist: requests (>=2.25.1)
Requires-Dist: python-dotenv (>=0.19.2)
